thetool/__init__.py
thetool/cli.py
thetool/metadata.py
thetool/commands/__init__.py
thetool/commands/clean.py
thetool/commands/info.py
thetool/commands/install.py
thetool/commands/list.py
thetool/commands/uninstall.py
thetool/commands/update.py
thetool/commands/upgrade.py
thetool/commands/version.py
thetool/helpers/__init__.py
thetool/helpers/cache.py
thetool/helpers/database.py
thetool/helpers/http.py
thetool/helpers/log.py
thetool/helpers/system.py
thetool/helpers/tool.py
thetool-0.2.0.dist-info/LICENSE
thetool-0.2.0.dist-info/METADATA
thetool-0.2.0.dist-info/WHEEL
thetool-0.2.0.dist-info/entry_points.txt
thetool-0.2.0.dist-info/top_level.txt
thetool-0.2.0.dist-info/RECORD
