Metadata-Version: 2.1
Name: thetool
Version: 0.2.0
Summary: Get and install tools from internet
Home-page: http://localhost/thetool
Download-URL: http://localhost/thetool
Author: Guillaume MARTINEZ
Author-email: lunik@tiwabbit.fr
Maintainer: Guillaume MARTINEZ
Maintainer-email: lunik@tiwabbit.fr
Classifier: Development Status :: 3 - Alpha
Classifier: Intended Audience :: Developers
Classifier: Intended Audience :: Information Technology
Classifier: Intended Audience :: System Administrators
Classifier: Topic :: Software Development :: Build Tools
Classifier: License :: OSI Approved :: GNU General Public License v3 (GPLv3)
Classifier: Programming Language :: Python :: 3
Classifier: Programming Language :: Python :: 3.8
Classifier: Programming Language :: Python :: 3.9
Classifier: Programming Language :: Python :: 3.10
Classifier: Programming Language :: Python :: 3.11
Requires-Python: >=3.8.0
License-File: LICENSE
Requires-Dist: requests ==2.*
Requires-Dist: requests-cache ==1.*
Requires-Dist: pyyaml ==6.*
Requires-Dist: GitPython ==3.*
Requires-Dist: packaging ==23.*
Provides-Extra: dev
Requires-Dist: pylint ; extra == 'dev'
Requires-Dist: build ; extra == 'dev'
Requires-Dist: pytest ; extra == 'dev'
Requires-Dist: pytest-cov ; extra == 'dev'
Requires-Dist: pytest-html ; extra == 'dev'
Requires-Dist: pytest-xdist ; extra == 'dev'
Requires-Dist: pytest-helpers-namespace ; extra == 'dev'
Requires-Dist: pytest-order ; extra == 'dev'
Requires-Dist: wheel ; extra == 'dev'
Requires-Dist: twine ; extra == 'dev'
